v/debouncer.v
module debouncer #(
    parameter CLK_FREQ = 50_000_000,
    parameter DEBOUNCE_TIME_MS = 20
)(
    input  wire clk_50Hz,
    input  wire btn_in,
    output reg  btn_out,
    output wire btn_pulse
);

    localparam integer COUNT_MAX = (CLK_FREQ / 1000) * DEBOUNCE_TIME_MS;
    localparam integer COUNT_W   = $clog2(COUNT_MAX);

    reg [COUNT_W-1:0] timer;
    reg sync_0, sync_1;
    reg btn_out_last;

    always @(posedge clk_50Hz) begin
        sync_0<=btn_in;
        sync_1<=sync_0;
    end

    // 2. Debounce
    always @(posedge clk_50Hz) begin
        if (sync_1 == btn_out) begin
            timer <= 0;
        end else begin
            if (timer == COUNT_MAX - 1) begin
                btn_out <= sync_1;
                timer   <= 0;
            end else begin
                timer <= timer + 1'b1;
            end
        end
    end

    // 3. Edge detection
    always @(posedge clk_50Hz) begin
        btn_out_last <= btn_out;
    end

    assign btn_pulse = btn_out & ~btn_out_last;

endmodule

v/debouncer_tb.v
`timescale 1ns/1ps

module debouncer_tb;
    reg clk;
    reg btn_in;

    wire btn_out;
    wire btn_pulse;

    debouncer #(
        .CLK_FREQ(1000),
        .DEBOUNCE_TIME_MS(4)
    ) dut (
        .clk_50Hz(clk),
        .btn_in(btn_in),
        .btn_out(btn_out),
        .btn_pulse(btn_pulse)
    );

    always #5 clk = ~clk;

    integer pulse_count;

    initial begin
        clk = 1'b0;
        btn_in = 1'b0;
        pulse_count = 0;
        dut.timer = 0;
        dut.sync_0 = 1'b0;
        dut.sync_1 = 1'b0;
        dut.btn_out_last = 1'b0;
        dut.btn_out = 1'b0;

        $dumpfile("debouncer_tb.vcd");
        $dumpvars(0, debouncer_tb);

        // Short pulse that should not remain stable long enough to debounce high.
        @(posedge clk);
        btn_in = 1'b1;
        @(posedge clk);
        btn_in = 1'b0;
        repeat (6) @(posedge clk);

        if (btn_out !== 1'b0) begin
            $display("FAIL: btn_out changed during short bounce burst");
            $fatal(1);
        end

        // Long stable press should produce one debounced high and one pulse.
        btn_in = 1'b1;
        repeat (8) @(posedge clk);

        if (btn_out !== 1'b1) begin
            $display("FAIL: btn_out did not debounce high");
            $fatal(1);
        end

        // Hold the press to ensure we do not get extra pulses.
        repeat (4) @(posedge clk);

        // Release and debounce back low.
        btn_in = 1'b0;
        repeat (8) @(posedge clk);

        if (btn_out !== 1'b0) begin
            $display("FAIL: btn_out did not debounce low");
            $fatal(1);
        end

        if (pulse_count !== 1) begin
            $display("FAIL: expected 1 pulse, got %0d", pulse_count);
            $fatal(1);
        end

        $display("debouncer_tb passed");
        $finish;
    end

    always @(posedge clk) begin
        if (btn_pulse)
            pulse_count <= pulse_count + 1;
    end
endmodule

debouncer_tb.vcd
$date
	Thu May  7 13:33:09 2026
$end
$version
	Icarus Verilog
$end
$timescale
	1ps
$end
$scope module debouncer_tb $end
$var wire 1 ! btn_pulse $end
$var wire 1 " btn_out $end
$var reg 1 # btn_in $end
$var reg 1 $ clk $end
$var integer 32 % pulse_count [31:0] $end
$scope module dut $end
$var wire 1 # btn_in $end
$var wire 1 ! btn_pulse $end
$var wire 1 $ clk_50Hz $end
$var parameter 32 & CLK_FREQ $end
$var parameter 32 ' COUNT_MAX $end
$var parameter 32 ( COUNT_W $end
$var parameter 32 ) DEBOUNCE_TIME_MS $end
$var reg 1 " btn_out $end
$var reg 1 * btn_out_last $end
$var reg 1 + sync_0 $end
$var reg 1 , sync_1 $end
$var reg 2 - timer [1:0] $end
$upscope $end
$upscope $end
$enddefinitions $end
$comment Show the parameter values. $end
$dumpall
b100 )
b10 (
b100 '
b1111101000 &
$end
#0
$dumpvars
b0 -
0,
0+
0*
b0 %
0$
0#
0"
0!
$end
#5000
1+
1#
1$
#10000
0$
#15000
1,
0#
1$
#20000
0$
#25000
0+
b1 -
1$
#30000
0$
#35000
b10 -
0,
1$
#40000
0$
#45000
b0 -
1$
#50000
0$
#55000
1$
#60000
0$
#65000
1$
#70000
0$
#75000
1#
1$
#80000
0$
#85000
1+
1$
#90000
0$
#95000
1,
1$
#100000
0$
#105000
b1 -
1$
#110000
0$
#115000
b10 -
1$
#120000
0$
#125000
b11 -
1$
#130000
0$
#135000
1!
b0 -
1"
1$
#140000
0$
#145000
0!
1*
b1 %
1$
#150000
0$
#155000
1$
#160000
0$
#165000
1$
#170000
0$
#175000
1$
#180000
0$
#185000
1$
#190000
0$
#195000
0#
1$
#200000
0$
#205000
0+
1$
#210000
0$
#215000
0,
1$
#220000
0$
#225000
b1 -
1$
#230000
0$
#235000
b10 -
1$
#240000
0$
#245000
b11 -
1$
#250000
0$
#255000
b0 -
0"
1$
#260000
0$
#265000
0*
1$
