v/fsm.v
module fsm( 
    input clk, 
    input srst, 

    input pause_pulse,
    input reset_pulse,
    input adj_level,
    input sel_level, 

    output reg running, 
    output reg paused,
    output reg do_reset, 
    output reg adj_mode, 
    output reg [1:0] sel_digit
); 

    parameter DIGIT0 = 3'b000;
    parameter DIGIT1 = 3'b001;
    parameter DIGIT2 = 3'b010;
    parameter DIGIT3 = 3'b011;
    parameter NORMAL = 3'b100;
    parameter PAUSE  = 3'b101;
    parameter RESET  = 3'b110;

    reg[2:0] state;
    reg[2:0] next_state;

    // state register
    always @(posedge clk or posedge srst) begin
        if (srst)
            state <= NORMAL;
        else
            state <= next_state;
    end

    // next-state logic
    always @(*) begin
        next_state = state;

        // highest-priority button action
        if (reset_pulse) begin
            next_state = RESET;
        end else begin
            case (state)
                NORMAL: begin
                    if (pause_pulse)
                        next_state = PAUSE;
                    else if (adj_level)
                        next_state = DIGIT0;
                end

                PAUSE: begin
                    if (pause_pulse)
                        next_state = NORMAL;
                    else if (adj_level)
                        next_state = DIGIT0;
                end

                RESET: begin
                    if (adj_level)
                        next_state = DIGIT0;
                    else
                        next_state = NORMAL;
                end

                DIGIT0: begin
                    if (!adj_level)
                        next_state = NORMAL;
                    else if (sel_level)
                        next_state = DIGIT1;
                end

                DIGIT1: begin
                    if (!adj_level)
                        next_state = NORMAL;
                    else if (sel_level)
                        next_state = DIGIT2;
                end

                DIGIT2: begin
                    if (!adj_level)
                        next_state = NORMAL;
                    else if (sel_level)
                        next_state = DIGIT3;
                end

                DIGIT3: begin
                    if (!adj_level)
                        next_state = NORMAL;
                    else if (sel_level)
                        next_state = DIGIT0;
                end

                default: begin
                    next_state = NORMAL;
                end
            endcase
        end
    end

    // output logic
    always @(*) begin
        running     = 1'b0;
        paused      = 1'b0;
        do_reset    = 1'b0;
        adj_mode    = 1'b0;
        sel_digit   = 2'b00;

        case (state)
            NORMAL: begin
                running = 1'b1;
            end

            PAUSE: begin
                paused = 1'b1;
            end

            RESET: begin
                do_reset = 1'b1;
            end

            DIGIT0: begin
                adj_mode  = 1'b1;
                sel_digit   = 2'b00;
            end

            DIGIT1: begin
                adj_mode  = 1'b1;
                sel_digit   = 2'b01;
            end

            DIGIT2: begin
                adj_mode  = 1'b1;
                sel_digit   = 2'b10;
            end

            DIGIT3: begin
                adj_mode  = 1'b1;
                sel_digit   = 2'b11;
            end
        endcase
    end
endmodule

v/fsm_tb.v
`timescale 1ns/1ps

module fsm_tb;
    reg clk;
    reg srst;
    reg pause_pulse;
    reg reset_pulse;
    reg adj_level;
    reg sel_level;

    wire running;
    wire paused;
    wire do_reset;
    wire adj_mode;
    wire [1:0] sel_digit;

    fsm dut (
        .clk(clk),
        .srst(srst),
        .pause_pulse(pause_pulse),
        .reset_pulse(reset_pulse),
        .adj_level(adj_level),
        .sel_level(sel_level),
        .running(running),
        .paused(paused),
        .do_reset(do_reset),
        .adj_mode(adj_mode),
        .sel_digit(sel_digit)
    );

    always #5 clk = ~clk;

    task expect_outputs;
        input exp_running;
        input exp_paused;
        input exp_reset;
        input exp_adj_mode;
        input [1:0] exp_sel_digit;
        input [127:0] label;
        begin
            #1;
            if (running !== exp_running ||
                paused !== exp_paused ||
                do_reset !== exp_reset ||
                adj_mode !== exp_adj_mode ||
                sel_digit !== exp_sel_digit) begin
                $display("FAIL: %0s", label);
                $display("  got      running=%b paused=%b do_reset=%b adj_mode=%b sel_digit=%b",
                    running, paused, do_reset, adj_mode, sel_digit);
                $display("  expected running=%b paused=%b do_reset=%b adj_mode=%b sel_digit=%b",
                    exp_running, exp_paused, exp_reset, exp_adj_mode, exp_sel_digit);
                $fatal(1);
            end
        end
    endtask

    task pulse_pause;
        begin
            pause_pulse = 1'b1;
            @(posedge clk);
            pause_pulse = 1'b0;
        end
    endtask

    task pulse_reset;
        begin
            reset_pulse = 1'b1;
            @(posedge clk);
            reset_pulse = 1'b0;
        end
    endtask

    task step_sel;
        begin
            sel_level = 1'b1;
            @(posedge clk);
            sel_level = 1'b0;
        end
    endtask

    initial begin
        clk         = 1'b0;
        srst        = 1'b1;
        pause_pulse = 1'b0;
        reset_pulse = 1'b0;
        adj_level   = 1'b0;
        sel_level   = 1'b0;

        $dumpfile("fsm_tb.vcd");
        $dumpvars(0, fsm_tb);

        @(posedge clk);
        srst = 1'b0;
        expect_outputs(1'b1, 1'b0, 1'b0, 1'b0, 2'b00, "reset -> NORMAL");

        pulse_pause();
        expect_outputs(1'b0, 1'b1, 1'b0, 1'b0, 2'b00, "pause from NORMAL -> PAUSE");

        pulse_pause();
        expect_outputs(1'b1, 1'b0, 1'b0, 1'b0, 2'b00, "pause from PAUSE -> NORMAL");

        adj_level = 1'b1;
        @(posedge clk);
        expect_outputs(1'b0, 1'b0, 1'b0, 1'b1, 2'b00, "enter DIGIT0");

        step_sel();
        expect_outputs(1'b0, 1'b0, 1'b0, 1'b1, 2'b01, "DIGIT0 -> DIGIT1");

        step_sel();
        expect_outputs(1'b0, 1'b0, 1'b0, 1'b1, 2'b10, "DIGIT1 -> DIGIT2");

        step_sel();
        expect_outputs(1'b0, 1'b0, 1'b0, 1'b1, 2'b11, "DIGIT2 -> DIGIT3");

        step_sel();
        expect_outputs(1'b0, 1'b0, 1'b0, 1'b1, 2'b00, "DIGIT3 -> DIGIT0");

        adj_level = 1'b0;
        @(posedge clk);
        expect_outputs(1'b1, 1'b0, 1'b0, 1'b0, 2'b00, "leave adjust mode -> NORMAL");

        pulse_reset();
        expect_outputs(1'b0, 1'b0, 1'b1, 1'b0, 2'b00, "reset pulse -> RESET");

        @(posedge clk);
        expect_outputs(1'b1, 1'b0, 1'b0, 1'b0, 2'b00, "RESET -> NORMAL");

        $display("fsm_tb passed");
        $finish;
    end
endmodule

fsm_tb.vcd
$date
	Thu May  7 13:30:35 2026
$end
$version
	Icarus Verilog
$end
$timescale
	1ps
$end
$scope module fsm_tb $end
$var wire 2 ! sel_digit [1:0] $end
$var wire 1 " running $end
$var wire 1 # paused $end
$var wire 1 $ do_reset $end
$var wire 1 % adj_mode $end
$var reg 1 & adj_level $end
$var reg 1 ' clk $end
$var reg 1 ( pause_pulse $end
$var reg 1 ) reset_pulse $end
$var reg 1 * sel_level $end
$var reg 1 + srst $end
$scope module dut $end
$var wire 1 & adj_level $end
$var wire 1 ' clk $end
$var wire 1 ( pause_pulse $end
$var wire 1 ) reset_pulse $end
$var wire 1 * sel_level $end
$var wire 1 + srst $end
$var parameter 3 , DIGIT0 $end
$var parameter 3 - DIGIT1 $end
$var parameter 3 . DIGIT2 $end
$var parameter 3 / DIGIT3 $end
$var parameter 3 0 NORMAL $end
$var parameter 3 1 PAUSE $end
$var parameter 3 2 RESET $end
$var reg 1 % adj_mode $end
$var reg 1 $ do_reset $end
$var reg 3 3 next_state [2:0] $end
$var reg 1 # paused $end
$var reg 1 " running $end
$var reg 2 4 sel_digit [1:0] $end
$var reg 3 5 state [2:0] $end
$upscope $end
$scope task expect_outputs $end
$var reg 1 6 exp_adj_mode $end
$var reg 1 7 exp_paused $end
$var reg 1 8 exp_reset $end
$var reg 1 9 exp_running $end
$var reg 2 : exp_sel_digit [1:0] $end
$var reg 128 ; label [127:0] $end
$upscope $end
$scope task pulse_pause $end
$upscope $end
$scope task pulse_reset $end
$upscope $end
$scope task step_sel $end
$upscope $end
$upscope $end
$enddefinitions $end
$comment Show the parameter values. $end
$dumpall
b110 2
b101 1
b100 0
b11 /
b10 .
b1 -
b0 ,
$end
#0
$dumpvars
bx ;
bx :
x9
x8
x7
x6
b100 5
b0 4
b100 3
1+
0*
0)
0(
0'
0&
0%
0$
0#
1"
b0 !
$end
#5000
b11100100110010101110011011001010111010000100000001011010011111000100000010011100100111101010010010011010100000101001100 ;
b0 :
06
08
07
19
0+
1'
#6000
b101 3
1(
#10000
0'
#15000
1#
0"
b101 5
b101 3
b100000010011100100111101010010010011010100000101001100001000000010110100111110001000000101000001000001010101010101001101000101 ;
17
09
0(
1'
#16000
b100 3
1(
#20000
0'
#25000
1"
0#
b100 5
b100 3
b100000010100000100000101010101010100110100010100100000001011010011111000100000010011100100111101010010010011010100000101001100 ;
07
19
0(
1'
#26000
b0 3
1&
#30000
0'
#35000
1%
0"
b0 5
b11001010110111001110100011001010111001000100000010001000100100101000111010010010101010000110000 ;
16
09
1'
#36000
b1 3
1*
#40000
0'
#45000
b1 !
b1 4
1%
b1 5
b1 3
b1000100010010010100011101001001010101000011000000100000001011010011111000100000010001000100100101000111010010010101010000110001 ;
b1 :
0*
1'
#46000
b10 3
1*
#50000
0'
#55000
b10 !
b10 4
1%
b10 5
b10 3
b1000100010010010100011101001001010101000011000100100000001011010011111000100000010001000100100101000111010010010101010000110010 ;
b10 :
0*
1'
#56000
b11 3
1*
#60000
0'
#65000
b11 !
b11 4
1%
b11 5
b11 3
b1000100010010010100011101001001010101000011001000100000001011010011111000100000010001000100100101000111010010010101010000110011 ;
b11 :
0*
1'
#66000
b0 3
1*
#70000
0'
#75000
b0 !
b0 4
1%
b0 5
b0 3
b1000100010010010100011101001001010101000011001100100000001011010011111000100000010001000100100101000111010010010101010000110000 ;
b0 :
0*
1'
#76000
b100 3
0&
#80000
0'
#85000
1"
0%
b100 5
b1110100001000000110110101101111011001000110010100100000001011010011111000100000010011100100111101010010010011010100000101001100 ;
06
19
1'
#86000
b110 3
1)
#90000
0'
#95000
1$
0"
b110 5
b100 3
b1110100001000000111000001110101011011000111001101100101001000000010110100111110001000000101001001000101010100110100010101010100 ;
18
09
0)
1'
#100000
0'
#105000
1"
0$
b100 5
b10100100100010101010011010001010101010000100000001011010011111000100000010011100100111101010010010011010100000101001100 ;
08
19
1'
